cw_rpa/__init__.py
cw_rpa/httpclient/__init__.py
cw_rpa/httpclient/constants.py
cw_rpa/httpclient/models.py
cw_rpa/httpclient/token.py
cw_rpa/input/__init__.py
cw_rpa/input/constants.py
cw_rpa/logger/__init__.py
cw_rpa/logger/constants.py
cw_rpa/logger/models.py
cw_rpa/logger/utils.py
cw_rpa-1.2.2.dist-info/licenses/LICENSE
cw_rpa-1.2.2.dist-info/METADATA
cw_rpa-1.2.2.dist-info/WHEEL
cw_rpa-1.2.2.dist-info/top_level.txt
cw_rpa-1.2.2.dist-info/RECORD
