Metadata-Version: 2.4
Name: cw-rpa
Version: 1.2.2
Summary: The cw-rpa package provides reusable functions/common utilities for developing CW RPA bots.
Author: ConnectWise
License-File: LICENSE
Requires-Dist: requests
Dynamic: author
Dynamic: description
Dynamic: description-content-type
Dynamic: license-file
Dynamic: requires-dist
Dynamic: summary
